setup.cfg
setup.py
lifx/__init__.py
lifx/client.py
lifx/color.py
lifx/device.py
lifx/group.py
lifx/network.py
lifx/protocol.py
lifx/util.py
lifx_sdk.egg-info/PKG-INFO
lifx_sdk.egg-info/SOURCES.txt
lifx_sdk.egg-info/dependency_links.txt
lifx_sdk.egg-info/pbr.json
lifx_sdk.egg-info/requires.txt
lifx_sdk.egg-info/top_level.txt