Metadata-Version: 1.0
Name: lifx-sdk
Version: 0.7
Summary: An SDK for local LAN control of bulbs, using Python
Home-page: http://www.danielhall.me/
Author: Daniel Hall
Author-email: python-lifx-sdk@danielhall.me
License: UNKNOWN
Platform: UNKNOWN
